{
  "project_info": {
    "project_number": "625334484144",
    "project_id": "mekongnetems-63ac1",
    "storage_bucket": "mekongnetems-63ac1.appspot.com"
  },
  "client": [
    {
      "client_info": {
        "mobilesdk_app_id": "1:625334484144:android:9eb109aa0bb6b33ae6cf75",
        "android_client_info": {
          "package_name": "com.mekongnet.ems"
        }
      },
      "oauth_client": [],
      "api_key": [
        {
          "current_key": "AIzaSyBiKxNIikzJZderUnKbtaQSR11UOL08Q7c"
        }
      ],
      "services": {
        "appinvite_service": {
          "other_platform_oauth_client": []
        }
      }
    }
  ],
  "configuration_version": "1"
}